odoo/addons/sql_export_mail/README.rst
odoo/addons/sql_export_mail/__init__.py
odoo/addons/sql_export_mail/__manifest__.py
odoo/addons/sql_export_mail/data/mail_template.xml
odoo/addons/sql_export_mail/i18n/ca.po
odoo/addons/sql_export_mail/i18n/fr.po
odoo/addons/sql_export_mail/i18n/it.po
odoo/addons/sql_export_mail/i18n/sql_export_mail.pot
odoo/addons/sql_export_mail/models/__init__.py
odoo/addons/sql_export_mail/models/sql_export.py
odoo/addons/sql_export_mail/readme/CONFIGURE.md
odoo/addons/sql_export_mail/readme/CONTRIBUTORS.md
odoo/addons/sql_export_mail/readme/DESCRIPTION.md
odoo/addons/sql_export_mail/static/description/icon.png
odoo/addons/sql_export_mail/static/description/index.html
odoo/addons/sql_export_mail/tests/__init__.py
odoo/addons/sql_export_mail/tests/test_sql_query_mail.py
odoo/addons/sql_export_mail/views/sql_export_view.xml
odoo_addon_sql_export_mail-18.0.1.0.0.3.dist-info/METADATA
odoo_addon_sql_export_mail-18.0.1.0.0.3.dist-info/WHEEL
odoo_addon_sql_export_mail-18.0.1.0.0.3.dist-info/top_level.txt
odoo_addon_sql_export_mail-18.0.1.0.0.3.dist-info/RECORD
