Metadata-Version: 2.1
Name: odoo-addon-sql_export_mail
Version: 18.0.1.0.0.3
Requires-Python: >=3.10
Requires-Dist: odoo-addon-sql_export==18.0.*
Requires-Dist: odoo==18.0.*
Summary: Send csv file generated by sql query by mail.
Home-page: https://github.com/OCA/reporting-engine
License: AGPL-3
Author: Akretion,GRAP,Odoo Community Association (OCA)
Author-email: support@odoo-community.org
Classifier: Programming Language :: Python
Classifier: Framework :: Odoo
Classifier: Framework :: Odoo :: 18.0
Classifier: License :: OSI Approved :: GNU Affero General Public License v3
